electronic_instrument_adapter_sdk
