Metadata-Version: 1.1
Name: electronic-instrument-adapter-sdk
Version: 0.2.1
Summary: SDK for Electronic Instrument Adapter
Home-page: https://github.com/aalvarezwindey/electronic_instrument_adapter_sdk
Author: Ariel Alvarez Windey & Gabriel Robles
Author-email: ajalvarez@fi.uba.ar
License: MIT
Download-URL: https://github.com/aalvarezwindey/electronic_instrument_adapter_sdk/archive/refs/tags/0.2.1.tar.gz
Keywords: SDK,ELECTRONIC,INSTRUMENT,ADAPTER,FIUBA
Platform: UNKNOWN
Classifier: Development Status :: 4 - Beta
Classifier: Intended Audience :: Developers
Classifier: Topic :: Software Development :: Build Tools
Classifier: License :: OSI Approved :: MIT License
Classifier: Programming Language :: Python :: 3.6
